odoo/addons/account_invoice_inter_company/README.rst
odoo/addons/account_invoice_inter_company/__init__.py
odoo/addons/account_invoice_inter_company/__manifest__.py
odoo/addons/account_invoice_inter_company/i18n/account_invoice_inter_company.pot
odoo/addons/account_invoice_inter_company/i18n/de.po
odoo/addons/account_invoice_inter_company/i18n/fr.po
odoo/addons/account_invoice_inter_company/models/__init__.py
odoo/addons/account_invoice_inter_company/models/account_invoice.py
odoo/addons/account_invoice_inter_company/models/res_company.py
odoo/addons/account_invoice_inter_company/models/res_config_settings.py
odoo/addons/account_invoice_inter_company/static/description/icon.png
odoo/addons/account_invoice_inter_company/tests/__init__.py
odoo/addons/account_invoice_inter_company/tests/inter_company_invoice.xml
odoo/addons/account_invoice_inter_company/tests/test_inter_company_invoice.py
odoo/addons/account_invoice_inter_company/views/res_config_settings_view.xml
odoo11_addon_account_invoice_inter_company-11.0.1.1.1.dist-info/METADATA
odoo11_addon_account_invoice_inter_company-11.0.1.1.1.dist-info/RECORD
odoo11_addon_account_invoice_inter_company-11.0.1.1.1.dist-info/WHEEL
odoo11_addon_account_invoice_inter_company-11.0.1.1.1.dist-info/top_level.txt
