Metadata-Version: 2.1
Name: odoo11-addon-account-invoice-inter-company
Version: 11.0.1.1.1
Summary: Intercompany invoice rules
Home-page: https://github.com/OCA/multi-company
Author: Odoo SA, Akretion, Odoo Community Association (OCA)
Author-email: support@odoo-community.org
License: AGPL-3
Platform: UNKNOWN
Classifier: Programming Language :: Python
Classifier: Framework :: Odoo
Classifier: License :: OSI Approved :: GNU Affero General Public License v3
Requires-Python: >=2.7, !=3.0.*, !=3.1.*, !=3.2.*, !=3.3.*, !=3.4.*
Requires-Dist: odoo11-addon-onchange-helper
Requires-Dist: odoo (<11.1dev,>=11.0a)
